mkdocs_autoapi/__init__.py
mkdocs_autoapi/autoapi.py
mkdocs_autoapi/logging.py
mkdocs_autoapi/plugin.py
mkdocs_autoapi/generate_files/__init__.py
mkdocs_autoapi/generate_files/editor.py
mkdocs_autoapi/generate_files/nav.py
mkdocs_autoapi/literate_nav/__init__.py
mkdocs_autoapi/literate_nav/exceptions.py
mkdocs_autoapi/literate_nav/globber.py
mkdocs_autoapi/literate_nav/parser.py
mkdocs_autoapi/literate_nav/resolve.py
mkdocs_autoapi/section_index/__init__.py
mkdocs_autoapi/section_index/rewrite.py
mkdocs_autoapi/section_index/section_page.py
mkdocs_autoapi-0.4.1.dist-info/licenses/LICENSE
mkdocs_autoapi-0.4.1.dist-info/METADATA
mkdocs_autoapi-0.4.1.dist-info/WHEEL
mkdocs_autoapi-0.4.1.dist-info/entry_points.txt
mkdocs_autoapi-0.4.1.dist-info/top_level.txt
mkdocs_autoapi-0.4.1.dist-info/RECORD
