Metadata-Version: 2.4
Name: mkdocs-autoapi
Version: 0.4.1
Summary: MkDocs plugin providing automatic API reference generation
Author-email: Jacob Ayers <jcayers20@gmail.com>
Project-URL: Changelog, https://github.com/jcayers20/mkdocs-autoapi/blob/main/CHANGELOG.md
Project-URL: Documentation, https://mkdocs-autoapi.readthedocs.io/en/0.2.1/
Project-URL: Repository, https://github.com/jcayers20/mkdocs-autoapi
Project-URL: Issues, https://github.com/jcayers20/mkdocs-autoapi/issues
Project-URL: License, https://github.com/jcayers20/mkdocs-autoapi/blob/main/LICENSE
Keywords: mkdocs,documentation,api,autoapi
Classifier: Development Status :: 4 - Beta
Classifier: Intended Audience :: Developers
Classifier: License :: OSI Approved :: MIT License
Classifier: Programming Language :: Python :: 3
Classifier: Programming Language :: Python :: 3.6
Classifier: Programming Language :: Python :: 3.7
Classifier: Programming Language :: Python :: 3.8
Classifier: Programming Language :: Python :: 3.9
Classifier: Programming Language :: Python :: 3.10
Classifier: Programming Language :: Python :: 3.11
Classifier: Programming Language :: Python :: 3.12
Requires-Python: >=3.6
License-File: LICENSE
Requires-Dist: mkdocs>=1.4.0
Requires-Dist: mkdocstrings>=0.19.0
Provides-Extra: python-legacy
Requires-Dist: mkdocstrings[python-legacy]>=0.19.0; extra == "python-legacy"
Provides-Extra: python
Requires-Dist: mkdocstrings[python]>=0.19.0; extra == "python"
Provides-Extra: vba
Requires-Dist: mkdocstrings-vba>=0.0.10; extra == "vba"
Dynamic: license-file
